{
    "assailIntervalMs": 1500,
    "expReward": 75,
    "aggroRange": 10,
    "moveIntervalMs": 1500,
    "name": "Mantis",
    "lootTableKeys": ["ew3Mantis", "enchantWeaponScroll2nd"],
    "scriptKeys": ["default", "setMonsterElement"],
    "scriptVars": {},
    "skillIntervalMs": 1500,
    "skillTemplateKeys": ["Assail"],
    "spellIntervalMs": 20000,
    "spellTemplateKeys": ["beag_sal", "beag_athar", "beag_creag", "beag_srad", "beag_cradh"],
    "sprite": 87,
    "statSheet": {
        "level": 14,
        "ac": 82,
        "maximumHp": 925,
        "maximumMp": 1000,
        "physicalAttack": 25,
        "magicAttack": 20,
        "con": 4,
        "dex": 1,
        "int": 15,
        "str": 12,
        "wis": 1
    },
    "templateKey": "ew3Mantis",
    "type": "Normal",
    "wanderIntervalMs": 2000
}