{
    "buyCost": 1500,
    "category": "armor",
    "color": "Blue",
    "isDyable": true,
    "displaySprite": 5,
    "equipmentType": "Armor",
    "gender": "Unisex",
    "maxDurability": 1000,
    "maxStacks": 1,
    "modifiers": {
        "ac": -8
    },
    "class": "priest",
    "pantsColor": "Black",
    "level": 1,
    "levelCircle": 1,
    "sellValue": 500,
    "weight": 4,
    "description": "An old, worn tunic",
    "name": "Cowl",
    "panelSprite": 100,
    "scriptKeys": ["Equipment"],
    "scriptVars": {
        "equipment": {}
    },
    "templateKey": "cowl"
}
